CHANGELOG
LICENSE
MANIFEST.in
README.md
setup.py
country_regions/__init__.py
country_regions/admin.py
country_regions/apps.py
country_regions/models.py
country_regions/tests.py
country_regions/views.py
country_regions/fixtures/initial_data.json
country_regions/migrations/0001_initial.py
country_regions/migrations/0002_data.py
country_regions/migrations/__init__.py
django_country_regions.egg-info/PKG-INFO
django_country_regions.egg-info/SOURCES.txt
django_country_regions.egg-info/dependency_links.txt
django_country_regions.egg-info/not-zip-safe
django_country_regions.egg-info/requires.txt
django_country_regions.egg-info/top_level.txt