Metadata-Version: 2.1
Name: django-country-regions
Version: 0.0.1
Summary: C
Home-page: https://github.com/afranck64/django-country-regions
Author: afranck64
License: MIT
Keywords: django countries regions
Platform: UNKNOWN
Classifier: Development Status :: 3 - Alpha
Classifier: Environment :: Web Environment
Classifier: Framework :: Django
Classifier: Intended Audience :: Developers
Classifier: License :: OSI Approved :: MIT License
Classifier: Operating System :: OS Independent
Classifier: Programming Language :: Python
Classifier: Programming Language :: Python :: 3
Classifier: Topic :: Internet :: WWW/HTTP
Classifier: Topic :: Software Development :: Libraries :: Python Modules
